pane/__init__.py
pane/annotations.py
pane/classes.py
pane/convert.py
pane/converters.py
pane/errors.py
pane/field.py
pane/io.py
pane/types.py
pane/util.py
pane/addons/__init__.py
pane/addons/numpy.py
py_pane-0.11.3.dist-info/licenses/LICENSE.txt
py_pane-0.11.3.dist-info/METADATA
py_pane-0.11.3.dist-info/WHEEL
py_pane-0.11.3.dist-info/top_level.txt
py_pane-0.11.3.dist-info/RECORD
