Metadata-Version: 2.4
Name: py-pane
Version: 0.11.3
Summary: A modern dataclass & data conversion library, focused on speed and expressiveness.
Author-email: Colin Gilgenbach <hexane@mit.edu>
License-Expression: MIT
Project-URL: Repository, https://github.com/hexane360/pane.git
Project-URL: Documentation, https://hexane360.github.io/pane/
Keywords: dataclass,validation,parsing,conversion
Classifier: Development Status :: 3 - Alpha
Classifier: Programming Language :: Python :: 3 :: Only
Classifier: Programming Language :: Python :: 3.9
Classifier: Programming Language :: Python :: 3.10
Classifier: Programming Language :: Python :: 3.11
Classifier: Programming Language :: Python :: 3.12
Classifier: Programming Language :: Python :: 3.13
Classifier: Typing :: Typed
Requires-Python: >=3.9
License-File: LICENSE.txt
Requires-Dist: PyYAML>=6.0
Requires-Dist: typing_extensions~=4.5
Provides-Extra: dev
Requires-Dist: pytest>=6.2.4; extra == "dev"
Requires-Dist: numpy; extra == "dev"
Provides-Extra: docs
Requires-Dist: mkdocs>=1.6.1; extra == "docs"
Requires-Dist: mkdocs-material==9.5.40; extra == "docs"
Requires-Dist: mkdocstrings[python]==0.26.1; extra == "docs"
Requires-Dist: markdown-include==0.8.1; extra == "docs"
Requires-Dist: mike==1.1.2; extra == "docs"
Dynamic: license-file
